[
    {
        "id": "01",
        "title": "深入浅出 testing-library",
        "description": "深入浅出 testing-library",
        "date": "2024-12-21",
        "themes": {
            "dark": "juejin-dark",
            "light": "jzman"
        }
    },
    {
        "id": "02",
        "title": "React 的 KeepAlive 探索",
        "description": "React 的 KeepAlive 探索",
        "date": "2024-12-21",
        "themes": {
            "dark": "juejin-dark",
            "light": "juejin-light"
        }
    }
]
